semaphoreci/__init__.py
semaphoreci/exceptions.py
semaphoreci/orm.py
semaphoreci/session.py
semaphoreci/utils.py
semaphoreci-0.1.0.dist-info/DESCRIPTION.rst
semaphoreci-0.1.0.dist-info/METADATA
semaphoreci-0.1.0.dist-info/metadata.json
semaphoreci-0.1.0.dist-info/RECORD
semaphoreci-0.1.0.dist-info/top_level.txt
semaphoreci-0.1.0.dist-info/WHEEL
